django_gss_spnego/__init__.py
django_gss_spnego/backends.py
django_gss_spnego/views.py
django_gss_spnego/__pycache__/__init__.cpython-39.pyc
django_gss_spnego/__pycache__/backends.cpython-39.pyc
django_gss_spnego/__pycache__/views.cpython-39.pyc
django_gss_spnego/templates/spnego.html
django_gss_spnego-21.10.1.dev0.dist-info/LICENSE
django_gss_spnego-21.10.1.dev0.dist-info/METADATA
django_gss_spnego-21.10.1.dev0.dist-info/WHEEL
django_gss_spnego-21.10.1.dev0.dist-info/top_level.txt
django_gss_spnego-21.10.1.dev0.dist-info/RECORD
